pydis/__init__.py
pydis/redis_dict.py
pydis/redis_list.py
pydis/redis_object.py
pydis/redis_set.py
pydis/redis_settings.py
pydis/redis_sortedset.py
pydis-0.8.2.dist-info/LICENSE
pydis-0.8.2.dist-info/METADATA
pydis-0.8.2.dist-info/WHEEL
pydis-0.8.2.dist-info/top_level.txt
pydis-0.8.2.dist-info/RECORD
